.deepsource.toml
.env-example
.gitignore
.pypirc
CONTRIBUTING.md
LICENSE
MANIFEST.in
README.md
TODO.md
cc.py
makefile
orm
orm.sqlite3
requirements.txt
setup.py
.github/ISSUE_TEMPLATE/bug_report.md
.github/ISSUE_TEMPLATE/feature_request.md
.github/workflows/pythonapp.yml
.github/workflows/pythonpublish.yml
app/observers/UserObserver.py
conda/conda_build_config.yaml
conda/meta.yaml
databases/migrations/2018_01_09_043202_create_users_table.py
databases/migrations/2020_04_17_000000_create_friends_table.py
databases/migrations/2020_04_17_00000_create_articles_table.py
databases/migrations/2020_10_20_152904_create_table_schema_migration.py
databases/migrations/__init__.py
databases/seeds/database_seeder.py
databases/seeds/user_table_seeder.py
src/masonite_orm.egg-info/PKG-INFO
src/masonite_orm.egg-info/SOURCES.txt
src/masonite_orm.egg-info/dependency_links.txt
src/masonite_orm.egg-info/entry_points.txt
src/masonite_orm.egg-info/requires.txt
src/masonite_orm.egg-info/top_level.txt
src/masoniteorm/.gitignore
src/masoniteorm/__init__.py
src/masoniteorm/config.py
src/masoniteorm/exceptions.py
src/masoniteorm/collection/Collection.py
src/masoniteorm/collection/__init__.py
src/masoniteorm/commands/CanOverrideConfig.py
src/masoniteorm/commands/CanOverrideOptionsDefault.py
src/masoniteorm/commands/Command.py
src/masoniteorm/commands/Entry.py
src/masoniteorm/commands/MakeMigrationCommand.py
src/masoniteorm/commands/MakeModelCommand.py
src/masoniteorm/commands/MakeModelDocstringCommand.py
src/masoniteorm/commands/MakeObserverCommand.py
src/masoniteorm/commands/MakeSeedCommand.py
src/masoniteorm/commands/MigrateCommand.py
src/masoniteorm/commands/MigrateRefreshCommand.py
src/masoniteorm/commands/MigrateResetCommand.py
src/masoniteorm/commands/MigrateRollbackCommand.py
src/masoniteorm/commands/MigrateStatusCommand.py
src/masoniteorm/commands/SeedRunCommand.py
src/masoniteorm/commands/ShellCommand.py
src/masoniteorm/commands/__init__.py
src/masoniteorm/commands/stubs/create_migration.stub
src/masoniteorm/commands/stubs/create_seed.stub
src/masoniteorm/commands/stubs/model.stub
src/masoniteorm/commands/stubs/observer.stub
src/masoniteorm/commands/stubs/table_migration.stub
src/masoniteorm/connections/.gitignore
