Metadata-Version: 2.1
Name: masonite-orm
Version: 3.0.0
Summary: The Official Masonite ORM
Home-page: https://github.com/masoniteframework/orm
Author: Joe Mancuso
Author-email: joe@masoniteproject.com
License: MIT
Keywords: Masonite,MasoniteFramework,Python,ORM
Classifier: Development Status :: 5 - Production/Stable
Classifier: Intended Audience :: Developers
Classifier: Topic :: Software Development :: Build Tools
Classifier: Environment :: Web Environment
Classifier: License :: OSI Approved :: MIT License
Classifier: Operating System :: OS Independent
Classifier: Programming Language :: Python :: 3.6
Classifier: Programming Language :: Python :: 3.7
Classifier: Programming Language :: Python :: 3.8
Classifier: Programming Language :: Python :: 3.9
Classifier: Framework :: Masonite
Classifier: Topic :: Software Development :: Libraries :: Python Modules
Classifier: Framework :: Masonite
License-File: LICENSE
Requires-Dist: inflection<0.6,>=0.3
Requires-Dist: pendulum<4.0,>=3.0
Requires-Dist: faker<14.0,>=4.1.0
Requires-Dist: cleo<0.9,>=0.8.0
Provides-Extra: test
Requires-Dist: coverage; extra == "test"
Requires-Dist: pytest; extra == "test"
